{
  "start_time": "2025-10-21T17:58:12.162456",
  "steps": [
    {
      "name": "view_inference",
      "number": 1,
      "start_time": "2025-10-21T17:59:51.340193",
      "result": {
        "compilation_error": false,
        "verified": 14,
        "errors": 2,
        "verus_errors": 3,
        "is_correct": false,
        "code_length": 17982
      },
      "execution_time": 176.6091706752777,
      "end_time": "2025-10-21T18:02:47.949371"
    },
    {
      "name": "view_refinement",
      "number": 2,
      "start_time": "2025-10-21T18:02:47.949493",
      "result": {
        "compilation_error": false,
        "verified": 14,
        "errors": 2,
        "verus_errors": 3,
        "is_correct": false,
        "code_length": 17982
      },
      "execution_time": 146.44152450561523,
      "end_time": "2025-10-21T18:05:14.391023"
    },
    {
      "name": "inv_inference",
      "number": 3,
      "start_time": "2025-10-21T18:05:14.391152",
      "result": {
        "compilation_error": false,
        "verified": 14,
        "errors": 2,
        "verus_errors": 3,
        "is_correct": false,
        "code_length": 17982
      },
      "execution_time": 748.1494009494781,
      "end_time": "2025-10-21T18:17:42.540557"
    },
    {
      "name": "spec_inference",
      "number": 4,
      "start_time": "2025-10-21T18:17:42.540692",
      "result": {
        "compilation_error": false,
        "verified": 15,
        "errors": 1,
        "verus_errors": 1,
        "is_correct": false,
        "code_length": 17465
      },
      "execution_time": 140.7255220413208,
      "end_time": "2025-10-21T18:20:03.266218"
    },
    {
      "name": "proof_generation",
      "number": 5,
      "start_time": "2025-10-21T18:20:03.266354",
      "result": {
        "compilation_error": false,
        "verified": 16,
        "errors": 0,
        "verus_errors": 0,
        "is_correct": true,
        "code_length": 10863
      },
      "execution_time": 86.23562717437744,
      "end_time": "2025-10-21T18:21:29.501985"
    }
  ],
  "repair_rounds": [],
  "final_result": {
    "compilation_error": false,
    "verified": 16,
    "errors": 0,
    "verus_errors": 0,
    "is_correct": true
  },
  "total_execution_time": 1397.348695,
  "end_time": "2025-10-21T18:21:29.511151"
}
