{
  "start_time": "2025-06-01T00:54:59.082910",
  "steps": [
    {
      "name": "view_inference",
      "number": 1,
      "start_time": "2025-06-01T00:55:09.410505",
      "result": {
        "compilation_error": true,
        "verified": -1,
        "errors": 999,
        "verus_errors": 1,
        "is_correct": false,
        "code_length": 3982
      },
      "execution_time": 67.33968377113342,
      "end_time": "2025-06-01T00:56:16.750212"
    },
    {
      "name": "view_refinement",
      "number": 2,
      "start_time": "2025-06-01T00:56:16.750337",
      "result": {
        "compilation_error": true,
        "verified": -1,
        "errors": 999,
        "verus_errors": 1,
        "is_correct": false,
        "code_length": 3674
      },
      "execution_time": 91.16423988342285,
      "end_time": "2025-06-01T00:57:47.914584"
    },
    {
      "name": "inv_inference",
      "number": 3,
      "start_time": "2025-06-01T00:57:47.914752",
      "result": {
        "compilation_error": true,
        "verified": -1,
        "errors": 999,
        "verus_errors": 1,
        "is_correct": false,
        "code_length": 3675
      },
      "execution_time": 50.5419807434082,
      "end_time": "2025-06-01T00:58:38.456738"
    },
    {
      "name": "spec_inference",
      "number": 4,
      "start_time": "2025-06-01T00:58:38.456887",
      "result": {
        "compilation_error": true,
        "verified": -1,
        "errors": 999,
        "verus_errors": 1,
        "is_correct": false,
        "code_length": 3673
      },
      "execution_time": 59.94572591781616,
      "end_time": "2025-06-01T00:59:38.402619"
    }
  ],
  "repair_rounds": [
    {
      "round_number": 1,
      "start_time": "2025-06-01T00:59:38.402885",
      "repairs": [
        {
          "error_type": "CompilationError",
          "repair_module": "repair_syntax",
          "before_score": {
            "compilation_error": true,
            "verified": -1,
            "errors": 999,
            "verus_errors": 1
          },
          "after_score": {
            "compilation_error": true,
            "verified": -1,
            "errors": 999,
            "verus_errors": 1
          },
          "success": false,
          "execution_time": 0.00014901161193847656
        }
      ],
      "end_time": "2025-06-01T00:59:38.507153",
      "execution_time": 0.104268
    },
    {
      "round_number": 2,
      "start_time": "2025-06-01T00:59:38.616422",
      "repairs": [
        {
          "error_type": "CompilationError",
          "repair_module": "repair_syntax",
          "before_score": {
            "compilation_error": true,
            "verified": -1,
            "errors": 999,
            "verus_errors": 1
          },
          "after_score": {
            "compilation_error": true,
            "verified": -1,
            "errors": 999,
            "verus_errors": 1
          },
          "success": false,
          "execution_time": 0.00015401840209960938
        },
        {
          "error_type": "ensure_private",
          "repair_module": "repair_postcond",
          "before_score": {
            "compilation_error": true,
            "verified": -1,
            "errors": 999,
            "verus_errors": 1
          },
          "after_score": {
            "compilation_error": true,
            "verified": -1,
            "errors": 999,
            "verus_errors": 1
          },
          "success": false,
          "execution_time": 0.0011010169982910156
        }
      ],
      "end_time": "2025-06-01T00:59:38.726209",
      "execution_time": 0.109787
    },
    {
      "round_number": 3,
      "start_time": "2025-06-01T00:59:38.726663",
      "repairs": [
        {
          "error_type": "CompilationError",
          "repair_module": "repair_syntax",
          "before_score": {
            "compilation_error": true,
            "verified": -1,
            "errors": 999,
            "verus_errors": 1
          },
          "after_score": {
            "compilation_error": true,
            "verified": -1,
            "errors": 999,
            "verus_errors": 1
          },
          "success": false,
          "execution_time": 0.00011086463928222656
        },
        {
          "error_type": "ensure_private",
          "repair_module": "repair_postcond",
          "before_score": {
            "compilation_error": true,
            "verified": -1,
            "errors": 999,
            "verus_errors": 1
          },
          "after_score": {
            "compilation_error": true,
            "verified": -1,
            "errors": 999,
            "verus_errors": 1
          },
          "success": false,
          "execution_time": 0.00023698806762695312
        }
      ],
      "end_time": "2025-06-01T00:59:38.835198",
      "execution_time": 0.108535
    },
    {
      "round_number": 4,
      "start_time": "2025-06-01T00:59:38.835695",
      "repairs": [
        {
          "error_type": "CompilationError",
          "repair_module": "repair_syntax",
          "before_score": {
            "compilation_error": true,
            "verified": -1,
            "errors": 999,
            "verus_errors": 1
          },
          "after_score": {
            "compilation_error": true,
            "verified": -1,
            "errors": 999,
            "verus_errors": 1
          },
          "success": false,
          "execution_time": 0.00012087821960449219
        },
        {
          "error_type": "ensure_private",
          "repair_module": "repair_postcond",
          "before_score": {
            "compilation_error": true,
            "verified": -1,
            "errors": 999,
            "verus_errors": 1
          },
          "after_score": {
            "compilation_error": true,
            "verified": -1,
            "errors": 999,
            "verus_errors": 1
          },
          "success": false,
          "execution_time": 0.00023698806762695312
        }
      ],
      "end_time": "2025-06-01T00:59:38.944702",
      "execution_time": 0.109007
    },
    {
      "round_number": 5,
      "start_time": "2025-06-01T00:59:38.945224",
      "repairs": [
        {
          "error_type": "CompilationError",
          "repair_module": "repair_syntax",
          "before_score": {
            "compilation_error": true,
            "verified": -1,
            "errors": 999,
            "verus_errors": 1
          },
          "after_score": {
            "compilation_error": true,
            "verified": -1,
            "errors": 999,
            "verus_errors": 1
          },
          "success": false,
          "execution_time": 0.0001220703125
        },
        {
          "error_type": "ensure_private",
          "repair_module": "repair_postcond",
          "before_score": {
            "compilation_error": true,
            "verified": -1,
            "errors": 999,
            "verus_errors": 1
          },
          "after_score": {
            "compilation_error": true,
            "verified": -1,
            "errors": 999,
            "verus_errors": 1
          },
          "success": false,
          "execution_time": 0.00023221969604492188
        }
      ],
      "end_time": "2025-06-01T00:59:39.057447",
      "execution_time": 0.112223
    },
    {
      "round_number": 6,
      "start_time": "2025-06-01T00:59:39.058111",
      "repairs": [
        {
          "error_type": "CompilationError",
          "repair_module": "repair_syntax",
          "before_score": {
            "compilation_error": true,
            "verified": -1,
            "errors": 999,
            "verus_errors": 1
          },
          "after_score": {
            "compilation_error": true,
            "verified": -1,
            "errors": 999,
            "verus_errors": 1
          },
          "success": false,
          "execution_time": 0.00011301040649414062
        },
        {
          "error_type": "ensure_private",
          "repair_module": "repair_postcond",
          "before_score": {
            "compilation_error": true,
            "verified": -1,
            "errors": 999,
            "verus_errors": 1
          },
          "after_score": {
            "compilation_error": true,
            "verified": -1,
            "errors": 999,
            "verus_errors": 1
          },
          "success": false,
          "execution_time": 0.00023484230041503906
        }
      ],
      "end_time": "2025-06-01T00:59:39.168211",
      "execution_time": 0.1101
    },
    {
      "round_number": 7,
      "start_time": "2025-06-01T00:59:39.168812",
      "repairs": [
        {
          "error_type": "CompilationError",
          "repair_module": "repair_syntax",
          "before_score": {
            "compilation_error": true,
            "verified": -1,
            "errors": 999,
            "verus_errors": 1
          },
          "after_score": {
            "compilation_error": true,
            "verified": -1,
            "errors": 999,
            "verus_errors": 1
          },
          "success": false,
          "execution_time": 0.0001220703125
        },
        {
          "error_type": "ensure_private",
          "repair_module": "repair_postcond",
          "before_score": {
            "compilation_error": true,
            "verified": -1,
            "errors": 999,
            "verus_errors": 1
          },
          "after_score": {
            "compilation_error": true,
            "verified": -1,
            "errors": 999,
            "verus_errors": 1
          },
          "success": false,
          "execution_time": 0.0002460479736328125
        }
      ],
      "end_time": "2025-06-01T00:59:39.277612",
      "execution_time": 0.1088
    }
  ],
  "final_result": {
    "compilation_error": true,
    "verified": -1,
    "errors": 999,
    "verus_errors": 1,
    "is_correct": false
  },
  "total_execution_time": 280.196081,
  "end_time": "2025-06-01T00:59:39.278991"
}