{
  "start_time": "2025-10-11T14:20:42.806295",
  "steps": [
    {
      "name": "view_inference",
      "number": 1,
      "start_time": "2025-10-11T14:20:56.564588",
      "result": {
        "compilation_error": false,
        "verified": 4,
        "errors": 4,
        "verus_errors": 8,
        "is_correct": false,
        "code_length": 7641
      },
      "execution_time": 98.24656200408936,
      "end_time": "2025-10-11T14:22:34.811158"
    },
    {
      "name": "view_refinement",
      "number": 2,
      "start_time": "2025-10-11T14:22:34.811278",
      "result": {
        "compilation_error": false,
        "verified": 4,
        "errors": 4,
        "verus_errors": 8,
        "is_correct": false,
        "code_length": 7667
      },
      "execution_time": 128.17361903190613,
      "end_time": "2025-10-11T14:24:42.984902"
    },
    {
      "name": "inv_inference",
      "number": 3,
      "start_time": "2025-10-11T14:24:42.985088",
      "result": {
        "compilation_error": false,
        "verified": 4,
        "errors": 4,
        "verus_errors": 8,
        "is_correct": false,
        "code_length": 7667
      },
      "execution_time": 90.50922894477844,
      "end_time": "2025-10-11T14:26:13.494321"
    },
    {
      "name": "spec_inference",
      "number": 4,
      "start_time": "2025-10-11T14:26:13.494456",
      "result": {
        "compilation_error": false,
        "verified": 3,
        "errors": 5,
        "verus_errors": 9,
        "is_correct": false,
        "code_length": 8666
      },
      "execution_time": 98.09737062454224,
      "end_time": "2025-10-11T14:27:51.591830"
    },
    {
      "name": "proof_generation",
      "number": 5,
      "start_time": "2025-10-11T14:27:51.592038",
      "result": {
        "compilation_error": false,
        "verified": 4,
        "errors": 4,
        "verus_errors": 7,
        "is_correct": false,
        "code_length": 9270
      },
      "execution_time": 176.4304120540619,
      "end_time": "2025-10-11T14:30:48.022454"
    }
  ],
  "repair_rounds": [],
  "final_result": {
    "compilation_error": false,
    "verified": 4,
    "errors": 4,
    "verus_errors": 7,
    "is_correct": false
  },
  "total_execution_time": 605.217497,
  "end_time": "2025-10-11T14:30:48.023792"
}
