{
  "start_time": "2025-10-30T21:42:31.814503",
  "steps": [
    {
      "name": "view_inference",
      "number": 1,
      "start_time": "2025-10-30T21:42:41.450076",
      "result": {
        "compilation_error": false,
        "verified": 14,
        "errors": 2,
        "verus_errors": 3,
        "is_correct": false,
        "code_length": 18539
      },
      "execution_time": 105.33946561813354,
      "end_time": "2025-10-30T21:44:26.789574"
    },
    {
      "name": "view_refinement",
      "number": 2,
      "start_time": "2025-10-30T21:44:26.789698",
      "result": {
        "compilation_error": false,
        "verified": 14,
        "errors": 2,
        "verus_errors": 3,
        "is_correct": false,
        "code_length": 18539
      },
      "execution_time": 98.79975843429565,
      "end_time": "2025-10-30T21:46:05.589461"
    },
    {
      "name": "inv_inference",
      "number": 3,
      "start_time": "2025-10-30T21:46:05.589587",
      "result": {
        "compilation_error": false,
        "verified": 14,
        "errors": 2,
        "verus_errors": 3,
        "is_correct": false,
        "code_length": 18545
      },
      "execution_time": 113.10954189300537,
      "end_time": "2025-10-30T21:47:58.699133"
    },
    {
      "name": "spec_inference",
      "number": 4,
      "start_time": "2025-10-30T21:47:58.699269",
      "result": {
        "compilation_error": true,
        "verified": -1,
        "errors": 999,
        "verus_errors": 1,
        "is_correct": false,
        "code_length": 18846
      },
      "execution_time": 98.35767817497253,
      "end_time": "2025-10-30T21:49:37.056951"
    },
    {
      "name": "proof_generation",
      "number": 5,
      "start_time": "2025-10-30T21:49:37.057091",
      "result": {
        "compilation_error": true,
        "verified": -1,
        "errors": 999,
        "verus_errors": 1,
        "is_correct": false,
        "code_length": 18950
      },
      "execution_time": 96.82236814498901,
      "end_time": "2025-10-30T21:51:13.879463"
    }
  ],
  "repair_rounds": [
    {
      "round_number": 1,
      "start_time": "2025-10-30T21:51:13.879702",
      "repairs": [
        {
          "error_type": "require_private",
          "repair_module": "repair_remove_inv",
          "before_score": {
            "compilation_error": true,
            "verified": -1,
            "errors": 999,
            "verus_errors": 1
          },
          "after_score": {
            "compilation_error": false,
            "verified": 14,
            "errors": 2,
            "verus_errors": 3
          },
          "success": true,
          "execution_time": 112.00686883926392
        }
      ],
      "end_time": "2025-10-30T21:53:05.895929",
      "execution_time": 112.016227
    },
    {
      "round_number": 2,
      "start_time": "2025-10-30T21:53:05.904670",
      "repairs": [
        {
          "error_type": "AssertFail",
          "repair_module": "repair_assertion",
          "before_score": {
            "compilation_error": false,
            "verified": 14,
            "errors": 2,
            "verus_errors": 3
          },
          "after_score": {
            "compilation_error": false,
            "verified": 14,
            "errors": 2,
            "verus_errors": 3
          },
          "success": false,
          "execution_time": 41.20083022117615
        },
        {
          "error_type": "PreCondFail",
          "repair_module": "repair_precond",
          "before_score": {
            "compilation_error": false,
            "verified": 14,
            "errors": 2,
            "verus_errors": 3
          },
          "after_score": {
            "compilation_error": false,
            "verified": 14,
            "errors": 2,
            "verus_errors": 3
          },
          "success": false,
          "execution_time": 105.97220969200134
        },
        {
          "error_type": "PostCondFail",
          "repair_module": "repair_postcond",
          "before_score": {
            "compilation_error": false,
            "verified": 14,
            "errors": 2,
            "verus_errors": 3
          },
          "after_score": {
            "compilation_error": false,
            "verified": 14,
            "errors": 2,
            "verus_errors": 3
          },
          "success": false,
          "execution_time": 167.73102259635925
        }
      ],
      "end_time": "2025-10-30T21:58:20.811854",
      "execution_time": 314.907184
    },
    {
      "round_number": 3,
      "start_time": "2025-10-30T21:58:20.820439",
      "repairs": [
        {
          "error_type": "AssertFail",
          "repair_module": "repair_assertion",
          "before_score": {
            "compilation_error": false,
            "verified": 14,
            "errors": 2,
            "verus_errors": 3
          },
          "after_score": {
            "compilation_error": true,
            "verified": -1,
            "errors": 999,
            "verus_errors": 1
          },
          "success": false,
          "execution_time": 29.428924798965454
        },
        {
          "error_type": "PostCondFail",
          "repair_module": "repair_postcond",
          "before_score": {
            "compilation_error": true,
            "verified": -1,
            "errors": 999,
            "verus_errors": 1
          },
          "after_score": {
            "compilation_error": true,
            "verified": -1,
            "errors": 999,
            "verus_errors": 1
          },
          "success": false,
          "execution_time": 66.73112607002258
        }
      ],
      "end_time": "2025-10-30T21:59:56.982527",
      "execution_time": 96.162088
    },
    {
      "round_number": 4,
      "start_time": "2025-10-30T21:59:56.982823",
      "repairs": [
        {
          "error_type": "Other",
          "repair_module": "repair_syntax",
          "before_score": {
            "compilation_error": true,
            "verified": -1,
            "errors": 999,
            "verus_errors": 1
          },
          "after_score": {
            "compilation_error": false,
            "verified": 14,
            "errors": 2,
            "verus_errors": 2
          },
          "success": true,
          "execution_time": 66.4538459777832
        }
      ],
      "end_time": "2025-10-30T22:01:03.437742",
      "execution_time": 66.454919
    },
    {
      "round_number": 5,
      "start_time": "2025-10-30T22:01:03.438136",
      "repairs": [
        {
          "error_type": "AssertFail",
          "repair_module": "repair_assertion",
          "before_score": {
            "compilation_error": false,
            "verified": 14,
            "errors": 2,
            "verus_errors": 2
          },
          "after_score": {
            "compilation_error": false,
            "verified": 14,
            "errors": 2,
            "verus_errors": 2
          },
          "success": false,
          "execution_time": 34.838043212890625
        }
      ],
      "end_time": "2025-10-30T22:01:38.277363",
      "execution_time": 34.839227
    }
  ],
  "final_result": {
    "compilation_error": false,
    "verified": 14,
    "errors": 2,
    "verus_errors": 2,
    "is_correct": false
  },
  "total_execution_time": 1146.472762,
  "end_time": "2025-10-30T22:01:38.287265"
}
