{
  "start_time": "2025-10-17T03:12:18.517805",
  "steps": [
    {
      "name": "view_inference",
      "number": 1,
      "start_time": "2025-10-17T03:12:33.003514",
      "result": {
        "compilation_error": false,
        "verified": 4,
        "errors": 4,
        "verus_errors": 8,
        "is_correct": false,
        "code_length": 7668
      },
      "execution_time": 101.90761876106262,
      "end_time": "2025-10-17T03:14:14.911140"
    },
    {
      "name": "view_refinement",
      "number": 2,
      "start_time": "2025-10-17T03:14:14.911264",
      "result": {
        "compilation_error": false,
        "verified": 4,
        "errors": 4,
        "verus_errors": 8,
        "is_correct": false,
        "code_length": 7668
      },
      "execution_time": 91.06095504760742,
      "end_time": "2025-10-17T03:15:45.972224"
    },
    {
      "name": "inv_inference",
      "number": 3,
      "start_time": "2025-10-17T03:15:45.972353",
      "result": {
        "compilation_error": false,
        "verified": 4,
        "errors": 4,
        "verus_errors": 8,
        "is_correct": false,
        "code_length": 7668
      },
      "execution_time": 98.2878110408783,
      "end_time": "2025-10-17T03:17:24.260168"
    },
    {
      "name": "spec_inference",
      "number": 4,
      "start_time": "2025-10-17T03:17:24.260299",
      "result": {
        "compilation_error": true,
        "verified": -1,
        "errors": 999,
        "verus_errors": 1,
        "is_correct": false,
        "code_length": 8099
      },
      "execution_time": 108.61643934249878,
      "end_time": "2025-10-17T03:19:12.876742"
    },
    {
      "name": "proof_generation",
      "number": 5,
      "start_time": "2025-10-17T03:19:12.876909",
      "result": {
        "compilation_error": true,
        "verified": -1,
        "errors": 999,
        "verus_errors": 1,
        "is_correct": false,
        "code_length": 9441
      },
      "execution_time": 124.36401915550232,
      "end_time": "2025-10-17T03:21:17.240933"
    }
  ],
  "repair_rounds": [
    {
      "round_number": 1,
      "start_time": "2025-10-17T03:21:17.241212",
      "repairs": [
        {
          "error_type": "Other",
          "repair_module": "repair_syntax",
          "before_score": {
            "compilation_error": true,
            "verified": -1,
            "errors": 999,
            "verus_errors": 1
          },
          "after_score": {
            "compilation_error": false,
            "verified": 4,
            "errors": 4,
            "verus_errors": 6
          },
          "success": true,
          "execution_time": 114.16466474533081
        }
      ],
      "end_time": "2025-10-17T03:23:11.882934",
      "execution_time": 114.641722
    },
    {
      "round_number": 2,
      "start_time": "2025-10-17T03:23:11.891341",
      "repairs": [
        {
          "error_type": "PreCondFailVecLen",
          "repair_module": "repair_precond",
          "before_score": {
            "compilation_error": false,
            "verified": 4,
            "errors": 4,
            "verus_errors": 6
          },
          "after_score": {
            "compilation_error": false,
            "verified": 4,
            "errors": 4,
            "verus_errors": 6
          },
          "success": false,
          "execution_time": 137.48716950416565
        },
        {
          "error_type": "AssertFail",
          "repair_module": "repair_assertion",
          "before_score": {
            "compilation_error": false,
            "verified": 4,
            "errors": 4,
            "verus_errors": 6
          },
          "after_score": {
            "compilation_error": false,
            "verified": 4,
            "errors": 4,
            "verus_errors": 6
          },
          "success": false,
          "execution_time": 52.42498469352722
        },
        {
          "error_type": "PostCondFail",
          "repair_module": "repair_postcond",
          "before_score": {
            "compilation_error": false,
            "verified": 4,
            "errors": 4,
            "verus_errors": 6
          },
          "after_score": {
            "compilation_error": false,
            "verified": 4,
            "errors": 4,
            "verus_errors": 6
          },
          "success": false,
          "execution_time": 103.81986570358276
        }
      ],
      "end_time": "2025-10-17T03:28:05.625375",
      "execution_time": 293.734034
    },
    {
      "round_number": 3,
      "start_time": "2025-10-17T03:28:05.633901",
      "repairs": [
        {
          "error_type": "AssertFail",
          "repair_module": "repair_assertion",
          "before_score": {
            "compilation_error": false,
            "verified": 4,
            "errors": 4,
            "verus_errors": 6
          },
          "after_score": {
            "compilation_error": false,
            "verified": 4,
            "errors": 4,
            "verus_errors": 6
          },
          "success": false,
          "execution_time": 47.89061784744263
        },
        {
          "error_type": "PostCondFail",
          "repair_module": "repair_postcond",
          "before_score": {
            "compilation_error": false,
            "verified": 4,
            "errors": 4,
            "verus_errors": 6
          },
          "after_score": {
            "compilation_error": true,
            "verified": -1,
            "errors": 999,
            "verus_errors": 1
          },
          "success": false,
          "execution_time": 110.09440326690674
        }
      ],
      "end_time": "2025-10-17T03:30:43.620311",
      "execution_time": 157.98641
    },
    {
      "round_number": 4,
      "start_time": "2025-10-17T03:30:43.628846",
      "repairs": [
        {
          "error_type": "Other",
          "repair_module": "repair_syntax",
          "before_score": {
            "compilation_error": true,
            "verified": -1,
            "errors": 999,
            "verus_errors": 1
          },
          "after_score": {
            "compilation_error": true,
            "verified": -1,
            "errors": 999,
            "verus_errors": 1
          },
          "success": false,
          "execution_time": 77.75220537185669
        }
      ],
      "end_time": "2025-10-17T03:32:01.382137",
      "execution_time": 77.753291
    },
    {
      "round_number": 5,
      "start_time": "2025-10-17T03:32:01.390421",
      "repairs": [
        {
          "error_type": "Other",
          "repair_module": "repair_syntax",
          "before_score": {
            "compilation_error": true,
            "verified": -1,
            "errors": 999,
            "verus_errors": 1
          },
          "after_score": {
            "compilation_error": true,
            "verified": -1,
            "errors": 999,
            "verus_errors": 1
          },
          "success": false,
          "execution_time": 138.29286313056946
        }
      ],
      "end_time": "2025-10-17T03:34:20.304160",
      "execution_time": 138.913739
    }
  ],
  "final_result": {
    "compilation_error": false,
    "verified": 4,
    "errors": 4,
    "verus_errors": 8,
    "is_correct": false
  },
  "total_execution_time": 1321.79615,
  "end_time": "2025-10-17T03:34:20.313955"
}
